{"nodes":[{"id":"president_layout","label":"layout.tsx","file_type":"code","source_file":"src/app/dashboard/president/layout.tsx","source_location":"L1"},{"id":"president_layout_presidentlayout","label":"PresidentLayout()","file_type":"code","source_file":"src/app/dashboard/president/layout.tsx","source_location":"L11"}],"edges":[{"source":"president_layout","target":"react","relation":"imports_from","confidence":"EXTRACTED","source_file":"src/app/dashboard/president/layout.tsx","source_location":"L1","weight":1},{"source":"president_layout","target":"navigation","relation":"imports_from","confidence":"EXTRACTED","source_file":"src/app/dashboard/president/layout.tsx","source_location":"L2","weight":1},{"source":"president_layout","target":"d_coding_practices_ydc_ydc_portal_src_utils_supabase_server_ts","relation":"imports_from","confidence":"EXTRACTED","source_file":"src/app/dashboard/president/layout.tsx","source_location":"L3","weight":1},{"source":"president_layout","target":"supabase_server_createclient","relation":"imports","confidence":"EXTRACTED","source_file":"src/app/dashboard/president/layout.tsx","source_location":"L3","weight":1},{"source":"president_layout","target":"d_coding_practices_ydc_ydc_portal_src_lib_admin_ts","relation":"imports_from","confidence":"EXTRACTED","source_file":"src/app/dashboard/president/layout.tsx","source_location":"L4","weight":1},{"source":"president_layout","target":"lib_admin_getadmincontext","relation":"imports","confidence":"EXTRACTED","source_file":"src/app/dashboard/president/layout.tsx","source_location":"L4","weight":1},{"source":"president_layout","target":"d_coding_practices_ydc_ydc_portal_src_components_dashboard_presidentnav_tsx","relation":"imports_from","confidence":"EXTRACTED","source_file":"src/app/dashboard/president/layout.tsx","source_location":"L5","weight":1},{"source":"president_layout","target":"d_coding_practices_ydc_ydc_portal_src_components_ui_pageheader_tsx","relation":"imports_from","confidence":"EXTRACTED","source_file":"src/app/dashboard/president/layout.tsx","source_location":"L6","weight":1},{"source":"president_layout","target":"lucide_react","relation":"imports_from","confidence":"EXTRACTED","source_file":"src/app/dashboard/president/layout.tsx","source_location":"L7","weight":1},{"source":"president_layout","target":"president_layout_presidentlayout","relation":"contains","confidence":"EXTRACTED","source_file":"src/app/dashboard/president/layout.tsx","source_location":"L11","weight":1}]}